fast_stringcase/__init__.py
fast_stringcase/fast_stringcase.cpython-313-i386-linux-musl.so
fast_stringcase/fast_stringcase.pyi
fast_stringcase/py.typed
fast_stringcase-1.2.0b6.dist-info/METADATA
fast_stringcase-1.2.0b6.dist-info/WHEEL
fast_stringcase-1.2.0b6.dist-info/top_level.txt
fast_stringcase-1.2.0b6.dist-info/RECORD
