Metadata-Version: 2.4
Name: fast_stringcase
Version: 1.2.0b6
Summary: C extension for string case conversions. The logic is ported from and based on stringcase == 1.2.0
Home-page: https://github.com/IshamMohamed/fast-stringcase/
Download-URL: https://pypi.org/project/fast-stringcase/
Author: Isham Mohamed
Author-email: isham.iqbal@icloud.com
License: MIT
Classifier: Programming Language :: Python :: 3
Classifier: Operating System :: OS Independent
Requires-Python: >=3.9
Dynamic: author
Dynamic: author-email
Dynamic: classifier
Dynamic: description
Dynamic: description-content-type
Dynamic: download-url
Dynamic: home-page
Dynamic: license
Dynamic: requires-python
Dynamic: summary
